Workbook
Name Aporte: Planilha1!$D$17
Name Qtd_Anos: Planilha1!$D$18
Name Rendimento_Carteira: Planilha1!$D$13
Name Taxa_Mensal: Planilha1!$D$19

Sheet Planilha1
B11: CONFIGURAÇÕES
B12: Salário | D12: 5000
B13: Rendimento Carteira | D13: 0.006
B14: Sugestão de Investimento | D14: =D12*30% -> 1500
B16: INVESTIMENTO MENSAL
B17: Quanto investir por mês? | D17: 500
B18: Por Quantos Anos? | D18: 5
B19: Taxa de Rendimento Mensal? | D19: 0.01079
B20: Patrimônio acumulado? | D20: =FV(Taxa_Mensal,Qtd_Anos*12,Aporte*-1) -> 41888.457
B21: Dividendos mensais? | D21: =D20*$D$13 -> 251.33074
B23: CENÁRIOS | D23: Dividendos
A24: 2 | B24: Quanto em 2 Anos | C24: =FV($D$19,$A24*12,$D$17*-1) -> 13613.814 | D24: =C24*Rendimento_Carteira -> 81.682882
A25: 5 | B25: Quanto em 5 Anos | C25: =FV($D$19,$A25*12,$D$17*-1) -> 41888.457 | D25: =C25*Rendimento_Carteira -> 251.33074
A26: 10 | B26: Quanto em 10 Anos | C26: =FV($D$19,$A26*12,$D$17*-1) -> 121642.11 | D26: =C26*Rendimento_Carteira -> 729.85264
A27: 20 | B27: Quanto em 20 Anos | C27: =FV($D$19,$A27*12,$D$17*-1) -> 562599.2 | D27: =C27*Rendimento_Carteira -> 3375.5952
A28: 30 | B28: Quanto em 30 Anos | C28: =FV($D$19,$A28*12,$D$17*-1) -> 2161084.8 | D28: =C28*Rendimento_Carteira -> 12966.509
B30: PERFIL | C30: Moderado
B31: VALOR A SER INVESTIDO POR MÊS | C31: =Aporte -> 500
B33: TIPO DE FII | C33: Percentual Sugerido | D33: Valores
B34: PAPEL | C34: =VLOOKUP(C30&"-"&B34,Planilha2!$A$1:$D$19,4,FALSE) -> 0.32 | D34: =C34*$C$31 -> 160
B35: TIJOLO | C35: =VLOOKUP($C$30&"-"&B35,Planilha2!$A$1:$D$19,4,FALSE) -> 0.35 | D35: =C35*$C$31 -> 175
B36: HÍBRIDOS | C36: =VLOOKUP($C$30&"-"&B36,Planilha2!$A$1:$D$19,4,FALSE) -> 0.08 | D36: =C36*$C$31 -> 40
B37: FOF's | C37: =VLOOKUP($C$30&"-"&B37,Planilha2!$A$1:$D$19,4,FALSE) -> 0.05 | D37: =C37*$C$31 -> 25
B38: DESENVOLVIMENTO | C38: =VLOOKUP($C$30&"-"&B38,Planilha2!$A$1:$D$19,4,FALSE) -> 0.1 | D38: =C38*$C$31 -> 50
B39: HOTELARIAS | C39: =VLOOKUP($C$30&"-"&B39,Planilha2!$A$1:$D$19,4,FALSE) -> 0.1 | D39: =C39*$C$31 -> 50
D40: =SUM(D34:D39) -> 500

Sheet Planilha2
A1: Chave Composta | B1: PERFIL | C1: TIPO DE FII | D1: %
A2: =$B$2&"-"&C2 -> Conservador-PAPEL | B2: Conservador | C2: PAPEL | D2: 0.3 | H2: %
A3: =$B$2&"-"&C3 -> Conservador-TIJOLO | B3: Conservador | C3: TIJOLO | D3: 0.5 | G3: Moderado-TIJOLO | H3: =VLOOKUP(G3,$A$1:$D$194,4,FALSE) -> 0.35
A4: =$B$2&"-"&C4 -> Conservador-HÍBRIDOS | B4: Conservador | C4: HÍBRIDOS | D4: 0.1
A5: =$B$2&"-"&C5 -> Conservador-FOF's | B5: Conservador | C5: FOF's | D5: 0.1
A6: =$B$2&"-"&C6 -> Conservador-DESENVOLVIMENTO | B6: Conservador | C6: DESENVOLVIMENTO | D6: 0
A7: =$B$2&"-"&C7 -> Conservador-HOTELARIAS | B7: Conservador | C7: HOTELARIAS | D7: 0
A8: =$B$8&"-"&C8 -> Moderado-PAPEL | B8: Moderado | C8: PAPEL | D8: 0.32
A9: =$B$8&"-"&C9 -> Moderado-TIJOLO | B9: Moderado | C9: TIJOLO | D9: 0.35
A10: =$B$8&"-"&C10 -> Moderado-HÍBRIDOS | B10: Moderado | C10: HÍBRIDOS | D10: 0.08
A11: =$B$8&"-"&C11 -> Moderado-FOF's | B11: Moderado | C11: FOF's | D11: 0.05
A12: =$B$8&"-"&C12 -> Moderado-DESENVOLVIMENTO | B12: Moderado | C12: DESENVOLVIMENTO | D12: 0.1
A13: =$B$8&"-"&C13 -> Moderado-HOTELARIAS | B13: Moderado | C13: HOTELARIAS | D13: 0.1
A14: =B14&"-"&C14 -> Agressivo-PAPEL | B14: Agressivo | C14: PAPEL | D14: 0.5
A15: =B15&"-"&C15 -> Agressivo-TIJOLO | B15: Agressivo | C15: TIJOLO | D15: 0.1
A16: =B16&"-"&C16 -> Agressivo-HÍBRIDOS | B16: Agressivo | C16: HÍBRIDOS | D16: 0.05
A17: =B17&"-"&C17 -> Agressivo-FOF's | B17: Agressivo | C17: FOF's | D17: 0.05
A18: =B18&"-"&C18 -> Agressivo-DESENVOLVIMENTO | B18: Agressivo | C18: DESENVOLVIMENTO | D18: 0.2
A19: =B19&"-"&C19 -> Agressivo-HOTELARIAS | B19: Agressivo | C19: HOTELARIAS | D19: 0.1
